studentvue_cli/studentvue_cli.py
studentvue_cli-0.8.dist-info/LICENSE
studentvue_cli-0.8.dist-info/METADATA
studentvue_cli-0.8.dist-info/WHEEL
studentvue_cli-0.8.dist-info/entry_points.txt
studentvue_cli-0.8.dist-info/top_level.txt
studentvue_cli-0.8.dist-info/RECORD
