Metadata-Version: 2.1
Name: studentvue-cli
Version: 0.8
Summary: description
Home-page: https://github.com/g-kienzle/studentvue_cli
Author: UNKNOWN
Author-email: UNKNOWN
License: MIT
Download-URL: https://github.com/g-kienzle/studentvue_cli/archive/v0.8.tar.gz
Platform: UNKNOWN
Requires-Dist: fire
Requires-Dist: datetime
Requires-Dist: studentvue
Requires-Dist: bullet
Requires-Dist: configparser
